{"nodes": [{"id": "e_pos_system_src_renderer_utils_currency_ts", "label": "currency.ts", "file_type": "code", "source_file": "E:\\POS System\\src\\renderer\\utils\\currency.ts", "source_location": "L1"}, {"id": "utils_currency_formatcurrency", "label": "formatCurrency()", "file_type": "code", "source_file": "E:\\POS System\\src\\renderer\\utils\\currency.ts", "source_location": "L2"}, {"id": "utils_currency_formatnumber", "label": "formatNumber()", "file_type": "code", "source_file": "E:\\POS System\\src\\renderer\\utils\\currency.ts", "source_location": "L6"}, {"id": "utils_currency_formatdate", "label": "formatDate()", "file_type": "code", "source_file": "E:\\POS System\\src\\renderer\\utils\\currency.ts", "source_location": "L10"}, {"id": "utils_currency_formatdatetime", "label": "formatDateTime()", "file_type": "code", "source_file": "E:\\POS System\\src\\renderer\\utils\\currency.ts", "source_location": "L15"}, {"id": "utils_currency_todaystr", "label": "todayStr()", "file_type": "code", "source_file": "E:\\POS System\\src\\renderer\\utils\\currency.ts", "source_location": "L20"}, {"id": "utils_currency_yesterday", "label": "yesterday()", "file_type": "code", "source_file": "E:\\POS System\\src\\renderer\\utils\\currency.ts", "source_location": "L24"}, {"id": "utils_currency_startofmonth", "label": "startOfMonth()", "file_type": "code", "source_file": "E:\\POS System\\src\\renderer\\utils\\currency.ts", "source_location": "L28"}, {"id": "utils_currency_percentchange", "label": "percentChange()", "file_type": "code", "source_file": "E:\\POS System\\src\\renderer\\utils\\currency.ts", "source_location": "L33"}], "edges": [{"source": "e_pos_system_src_renderer_utils_currency_ts", "target": "utils_currency_formatcurrency", "relation": "contains", "confidence": "EXTRACTED", "source_file": "E:\\POS System\\src\\renderer\\utils\\currency.ts", "source_location": "L2", "weight": 1.0}, {"source": "e_pos_system_src_renderer_utils_currency_ts", "target": "utils_currency_formatnumber", "relation": "contains", "confidence": "EXTRACTED", "source_file": "E:\\POS System\\src\\renderer\\utils\\currency.ts", "source_location": "L6", "weight": 1.0}, {"source": "e_pos_system_src_renderer_utils_currency_ts", "target": "utils_currency_formatdate", "relation": "contains", "confidence": "EXTRACTED", "source_file": "E:\\POS System\\src\\renderer\\utils\\currency.ts", "source_location": "L10", "weight": 1.0}, {"source": "e_pos_system_src_renderer_utils_currency_ts", "target": "utils_currency_formatdatetime", "relation": "contains", "confidence": "EXTRACTED", "source_file": "E:\\POS System\\src\\renderer\\utils\\currency.ts", "source_location": "L15", "weight": 1.0}, {"source": "e_pos_system_src_renderer_utils_currency_ts", "target": "utils_currency_todaystr", "relation": "contains", "confidence": "EXTRACTED", "source_file": "E:\\POS System\\src\\renderer\\utils\\currency.ts", "source_location": "L20", "weight": 1.0}, {"source": "e_pos_system_src_renderer_utils_currency_ts", "target": "utils_currency_yesterday", "relation": "contains", "confidence": "EXTRACTED", "source_file": "E:\\POS System\\src\\renderer\\utils\\currency.ts", "source_location": "L24", "weight": 1.0}, {"source": "e_pos_system_src_renderer_utils_currency_ts", "target": "utils_currency_startofmonth", "relation": "contains", "confidence": "EXTRACTED", "source_file": "E:\\POS System\\src\\renderer\\utils\\currency.ts", "source_location": "L28", "weight": 1.0}, {"source": "e_pos_system_src_renderer_utils_currency_ts", "target": "utils_currency_percentchange", "relation": "contains", "confidence": "EXTRACTED", "source_file": "E:\\POS System\\src\\renderer\\utils\\currency.ts", "source_location": "L33", "weight": 1.0}], "raw_calls": [{"caller_nid": "utils_currency_formatcurrency", "callee": "toLocaleString", "is_member_call": true, "source_file": "E:\\POS System\\src\\renderer\\utils\\currency.ts", "source_location": "L3"}, {"caller_nid": "utils_currency_formatnumber", "callee": "toLocaleString", "is_member_call": true, "source_file": "E:\\POS System\\src\\renderer\\utils\\currency.ts", "source_location": "L7"}, {"caller_nid": "utils_currency_formatdate", "callee": "toLocaleDateString", "is_member_call": true, "source_file": "E:\\POS System\\src\\renderer\\utils\\currency.ts", "source_location": "L12"}, {"caller_nid": "utils_currency_formatdatetime", "callee": "toLocaleString", "is_member_call": true, "source_file": "E:\\POS System\\src\\renderer\\utils\\currency.ts", "source_location": "L17"}, {"caller_nid": "utils_currency_todaystr", "callee": "split", "is_member_call": true, "source_file": "E:\\POS System\\src\\renderer\\utils\\currency.ts", "source_location": "L21"}, {"caller_nid": "utils_currency_todaystr", "callee": "toISOString", "is_member_call": true, "source_file": "E:\\POS System\\src\\renderer\\utils\\currency.ts", "source_location": "L21"}, {"caller_nid": "utils_currency_yesterday", "callee": "split", "is_member_call": true, "source_file": "E:\\POS System\\src\\renderer\\utils\\currency.ts", "source_location": "L25"}, {"caller_nid": "utils_currency_yesterday", "callee": "toISOString", "is_member_call": true, "source_file": "E:\\POS System\\src\\renderer\\utils\\currency.ts", "source_location": "L25"}, {"caller_nid": "utils_currency_yesterday", "callee": "now", "is_member_call": true, "source_file": "E:\\POS System\\src\\renderer\\utils\\currency.ts", "source_location": "L25"}, {"caller_nid": "utils_currency_startofmonth", "callee": "getFullYear", "is_member_call": true, "source_file": "E:\\POS System\\src\\renderer\\utils\\currency.ts", "source_location": "L30"}, {"caller_nid": "utils_currency_startofmonth", "callee": "padStart", "is_member_call": true, "source_file": "E:\\POS System\\src\\renderer\\utils\\currency.ts", "source_location": "L30"}, {"caller_nid": "utils_currency_startofmonth", "callee": "String", "is_member_call": false, "source_file": "E:\\POS System\\src\\renderer\\utils\\currency.ts", "source_location": "L30"}, {"caller_nid": "utils_currency_startofmonth", "callee": "getMonth", "is_member_call": true, "source_file": "E:\\POS System\\src\\renderer\\utils\\currency.ts", "source_location": "L30"}]}